MANIFEST.in
README.md
setup.cfg
setup.py
templates/code.html
templates/download.html
templates/error.html
templates/favicon.png
templates/favicon2.png
templates/head.html
templates/help.html
templates/index.html
tmper/__init__.py
tmper/__main__.py
tmper/db.py
tmper/files.py
tmper/progress.py
tmper/util.py
tmper/web.py
tmper.egg-info/PKG-INFO
tmper.egg-info/SOURCES.txt
tmper.egg-info/dependency_links.txt
tmper.egg-info/entry_points.txt
tmper.egg-info/not-zip-safe
tmper.egg-info/requires.txt
tmper.egg-info/top_level.txt
tmper/../README.md
tmper/../templates/code.html
tmper/../templates/download.html
tmper/../templates/error.html
tmper/../templates/favicon.png
tmper/../templates/favicon2.png
tmper/../templates/head.html
tmper/../templates/help.html
tmper/../templates/index.html