Metadata-Version: 1.1
Name: tmper
Version: 0.5.7
Summary: Temporary file sharing using simple two digit codes.
Home-page: https://github.com/mattbierbaum/tmper
Author: Matt Bierbaum
Author-email: UNKNOWN
License: MIT License
Platform: osx
Platform: posix
Platform: linux
Platform: windows
Classifier: Development Status :: 3 - Alpha
Classifier: Intended Audience :: Developers
Classifier: License :: OSI Approved :: MIT License
Classifier: Programming Language :: Python :: 2
Classifier: Programming Language :: Python :: 2.7
Classifier: Programming Language :: Python :: 3
Classifier: Programming Language :: Python :: 3.4
Classifier: Programming Language :: Python :: 3.5
Classifier: Programming Language :: Python :: 3.6
